napari_turing/__init__.py
napari_turing/_widget.py
napari_turing/build_model.py
napari_turing/napari.yaml
napari_turing/Models/Brusselator.py
napari_turing/Models/FitzHughNagumo.py
napari_turing/Models/GameOfLife.py
napari_turing/Models/GrayScott.py
napari_turing/Models/ModelTemplate.py
napari_turing/Models/_TuringPattern.py
napari_turing/Models/_model_list.py
napari_turing/_tests/__init__.py
napari_turing/_tests/test_widget.py
napari_turing-0.3.2.dist-info/LICENSE
napari_turing-0.3.2.dist-info/METADATA
napari_turing-0.3.2.dist-info/WHEEL
napari_turing-0.3.2.dist-info/entry_points.txt
napari_turing-0.3.2.dist-info/top_level.txt
napari_turing-0.3.2.dist-info/RECORD
